fast_html/__init__.py
fast_html/py.typed
fast_html/utils.py
fast_html-1.0.12.dist-info/LICENSE
fast_html-1.0.12.dist-info/METADATA
fast_html-1.0.12.dist-info/WHEEL
fast_html-1.0.12.dist-info/RECORD
