Metadata-Version: 2.1
Name: fast_html
Version: 1.0.12
Summary: A fast, minimalist HTML generator
Home-page: https://github.com/pcarbonn/fast_html
License: LGPL-3.0-or-later
Keywords: HTML,HTMX
Author: Pierre
Author-email: pierre.carbonnelle@gmail.com
Requires-Python: >=3.7,<4.0
Classifier: Development Status :: 5 - Production/Stable
Classifier: License :: OSI Approved :: GNU Lesser General Public License v3 or later (LGPLv3+)
Classifier: Programming Language :: Python :: 3
Classifier: Programming Language :: Python :: 3.7
Classifier: Programming Language :: Python :: 3.8
Classifier: Programming Language :: Python :: 3.9
Classifier: Programming Language :: Python :: 3.10
Classifier: Programming Language :: Python :: 3.11
Classifier: Programming Language :: Python :: 3.12
Classifier: Programming Language :: Python :: 3.13
Classifier: Topic :: Internet :: WWW/HTTP
Classifier: Topic :: Text Processing :: Markup :: HTML
Project-URL: Repository, https://github.com/pcarbonn/fast_html
